rowingdata/2016-03-25-0758.CSV
rowingdata/2016-03-25-0758.TCX
rowingdata/2016-03-25-0758_data.CSV
rowingdata/2x20min_o.csv
rowingdata/3km_cd_o.csv
rowingdata/4x1km_corrected.csv
rowingdata/RP_testdata.csv
rowingdata/TrainingCenterDatabasev2.xsd
rowingdata/__init__.py
rowingdata/__main__.py
rowingdata/boatedit.py
rowingdata/copystats.py
rowingdata/crewnerd_interval.csv
rowingdata/crewnerdplot.py
rowingdata/crewnerdplottime.py
rowingdata/defaultrower.txt
rowingdata/ergdataplot.py
rowingdata/ergdataplottime.py
rowingdata/ergdatatotcx.py
rowingdata/ergstickplot.py
rowingdata/ergstickplottime.py
rowingdata/ergsticktotcx.py
rowingdata/example.csv
rowingdata/example_data.csv
rowingdata/gekkepainsled.csv
rowingdata/gmap_plot.html
rowingdata/hrpaceplot.html
rowingdata/konkatenaadje.py
rowingdata/lines.html
rowingdata/my1x.txt
rowingdata/otwplot.py
rowingdata/painsled_desktop_example.csv
rowingdata/painsled_desktop_plot.py
rowingdata/painsled_desktop_plottime.py
rowingdata/painsled_desktop_toc2.py
rowingdata/painsled_out_data.csv
rowingdata/painsled_to_csv_20160221-105218_erg-400150318_760465m.csv
rowingdata/painsledplot.py
rowingdata/painsledplot2.py
rowingdata/painsledplottime.py
rowingdata/painsledtoc2.py
rowingdata/roweredit.py
rowingdata/rowingdata-scripts.py
rowingdata/rowingdata.py
rowingdata/rowproplot.py
rowingdata/rowproplottime.py
rowingdata/rp_out.csv
rowingdata/sander.txt
rowingdata/single2.txt
rowingdata/speedcoachplot.py
rowingdata/speedcoachplottime.py
rowingdata/speedcoachtoc2.py
rowingdata/tcxplot.py
rowingdata/tcxplot_nogeo.py
rowingdata/tcxplottime.py
rowingdata/tcxplottime_nogeo.py
rowingdata/tcxtoc2.py
rowingdata/testdata.csv
rowingdata/testdata2.csv
rowingdata/testrp.py
rowingdata/trainingparser.py
rowingdata/windcorrected.py
rowingdata/writetcx.py
rowingdata-0.92.1.data/scripts/crewnerdplot.py
rowingdata-0.92.1.data/scripts/crewnerdplottime.py
rowingdata-0.92.1.dist-info/DESCRIPTION.rst
rowingdata-0.92.1.dist-info/METADATA
rowingdata-0.92.1.dist-info/RECORD
rowingdata-0.92.1.dist-info/WHEEL
rowingdata-0.92.1.dist-info/entry_points.txt
rowingdata-0.92.1.dist-info/metadata.json
rowingdata-0.92.1.dist-info/top_level.txt
