Metadata-Version: 2.0
Name: rowingdata
Version: 0.92.1
Summary: The rowingdata library to create colorful plots from CrewNerd, Painsled and other rowing data tools
Home-page: http://rowsandall.wordpress.com
Author: Sander Roosendaal
Author-email: roosendaalsander@gmail.com
License: MIT
Keywords: rowing ergometer concept2
Platform: UNKNOWN
Requires-Dist: docopt
Requires-Dist: iso8601
Requires-Dist: matplotlib
Requires-Dist: mechanize
Requires-Dist: numpy
Requires-Dist: pandas
Requires-Dist: python-dateutil
Requires-Dist: rowingphysics (>=0.2.3)
Requires-Dist: scipy
Requires-Dist: tqdm
